{
  "color": {
    "base": {
      "secondary": {
        "value": "#3717b8"
      },
      "primary": {
        "value": "#b51515"
      }
    },
    "text": {
      "value": "#232323"
    }
  },
  "font": {
    "base": {
      "paragraph": {
        "value": {
          "fontFamily": "Inter",
          "fontSize": 16,
          "fontWeight": 400,
          "letterSpacing": 0,
          "lineHeight": "18.75px",
          "color": "{color.text.value}"
        }
      },
      "subtitle": {
        "value": {
          "fontFamily": "Inter",
          "fontSize": 24,
          "fontWeight": 500,
          "letterSpacing": 0,
          "lineHeight": "28.125px",
          "color": "{color.text.value}"
        }
      },
      "header": {
        "value": {
          "fontFamily": "Inter",
          "fontSize": 36,
          "fontWeight": 400,
          "letterSpacing": 0,
          "lineHeight": "42.1875px",
          "color": "{color.text.value}"
        }
      }
    },
    "highlight": {
      "paragraph": {
        "value": {
          "fontFamily": "Inter",
          "fontSize": 16,
          "fontWeight": 400,
          "letterSpacing": 0,
          "lineHeight": "18.75px",
          "color": "{color.base.primary.value}"
        }
      },
      "subtitle": {
        "value": {
          "fontFamily": "Inter",
          "fontSize": 24,
          "fontWeight": 500,
          "letterSpacing": 0,
          "lineHeight": "28.125px",
          "color": "{color.base.primary.value}"
        }
      },
      "header": {
        "value": {
          "fontFamily": "Inter",
          "fontSize": 36,
          "fontWeight": 400,
          "letterSpacing": 0,
          "lineHeight": "42.1875px",
          "color": "{color.base.primary.value}"
        }
      }
    }
  }
}